[
    { "id": "2", "value": "Canada", "label": "Canada"},
    { "id": "3", "value": "Ireland", "label": "Ireland"},
    { "id": "4", "value": "Israel", "label": "Israel"},
    { "id": "5", "value": "Japan", "label": "Japan"},
    { "id": "6", "value": "The Netherlands", "label": "The Netherlands"},
    { "id": "7", "value": "Scotland", "label": "Scotland"},
    { "id": "8", "value": "United States", "label": "United States"},
    { "id": "9", "value": "Wales", "label": "Wales"},
    { "id": "10", "value": "Czech Republic", "label": "Czech Republic"},
    { "id": "11", "value": "India", "label": "India"},
    { "id": "12", "value": "Finland", "label": "Finland"},
    { "id": "13", "value": "Taiwan", "label": "Taiwan"},
    { "id": "14", "value": "Australia", "label": "Australia"},
    { "id": "15", "value": "France", "label": "France"},
    { "id": "16", "value": "England", "label": "England"},
    { "id": "17", "value": "Georgia", "label": "Georgia"}
]
